stackstr/__init__.py
stackstr/exception.py
stackstr/stackstr_client.py
stackstr_sdk-0.1.2.dist-info/METADATA
stackstr_sdk-0.1.2.dist-info/WHEEL
stackstr_sdk-0.1.2.dist-info/top_level.txt
stackstr_sdk-0.1.2.dist-info/RECORD
